.pre-commit-config.yaml
LICENSE
MANIFEST.in
README.md
environment_crossplatform_20250903_122335.yml
requirements.txt
setup.cfg
setup.py
hitif_ops/__init__.py
hitif_ops.egg-info/PKG-INFO
hitif_ops.egg-info/SOURCES.txt
hitif_ops.egg-info/dependency_links.txt
hitif_ops.egg-info/not-zip-safe
hitif_ops.egg-info/requires.txt
hitif_ops.egg-info/top_level.txt
hitif_ops/ml/__init__.py
hitif_ops/ml/models.py
hitif_ops/ml/preprocessing.py
hitif_ops/utils/__init__.py
hitif_ops/utils/data_utils.py
hitif_ops/utils/file_utils.py
hitif_ops/viz/__init__.py
hitif_ops/viz/charts.py
hitif_ops/viz/plots.py